setup.cfg
setup.py
Expressy.egg-info/PKG-INFO
Expressy.egg-info/SOURCES.txt
Expressy.egg-info/dependency_links.txt
Expressy.egg-info/top_level.txt
expressy/__init__.py
expressy/constant.py
expressy/expression.py
expressy/importer.py
expressy/quotes.py
expressy/units.py
expressy/value.py
expressy/ast_handlers/__init__.py
expressy/ast_handlers/expressions.py
expressy/ast_handlers/literals.py
expressy/ast_handlers/operators.py
expressy/ast_handlers/subscripting.py
expressy/ast_handlers/variables.py